HostsLexer.py
context.py
hostsman.py
utils.py
hostsman-1.1.3.dist-info/DESCRIPTION.rst
hostsman-1.1.3.dist-info/METADATA
hostsman-1.1.3.dist-info/RECORD
hostsman-1.1.3.dist-info/WHEEL
hostsman-1.1.3.dist-info/entry_points.txt
hostsman-1.1.3.dist-info/metadata.json
hostsman-1.1.3.dist-info/top_level.txt
